mosydbschema/__init__.py
mosydbschema/_version.py
mosydbschema/validator.py
mosydbschema/data/test.json
mosydbschema/schema/event.json
mosydbschema/schema/experiment.json
mosydbschema/schema/group.json
mosydbschema/schema/item.json
mosydbschema/schema/test.json
mosydbschema/schema/user.json
mosydbschema/schema/helper/personame.json
mosydbschema/schema/helper/time.json
mosydbschema/schema/helper/value.json
test/__init__.py
test/test_validator.py
mosydbschema-0.1.0.dist-info/AUTHORS.rst
mosydbschema-0.1.0.dist-info/LICENSE
mosydbschema-0.1.0.dist-info/METADATA
mosydbschema-0.1.0.dist-info/WHEEL
mosydbschema-0.1.0.dist-info/entry_points.txt
mosydbschema-0.1.0.dist-info/top_level.txt
mosydbschema-0.1.0.dist-info/RECORD
