Metadata-Version: 2.1
Name: mosydbschema
Version: 0.1.0
Summary: Schema package for material synthesis procedures
Home-page: https://github.com/GENESIS-EFRC/mosydb-schema
Author: Billinge Group
Author-email: sb2896@columbia.edu
License: BSD (3-clause)
Platform: UNKNOWN
Classifier: Development Status :: 2 - Pre-Alpha
Classifier: Natural Language :: English
Classifier: Programming Language :: Python :: 3
Requires-Python: >=3.6
Requires-Dist: jsonschema
Requires-Dist: pathlib
